{"cameraMode":{"drawMode":0,"name":"Shaded","section":"Shading Mode"},"sceneLighting":true,"audioPlay":false,"sceneViewState":{"m_AlwaysRefresh":false,"showFog":true,"showSkybox":true,"showFlares":true,"showImageEffects":true,"showParticleSystems":true,"showVisualEffectGraphs":true,"m_FxEnabled":true},"in2DMode":false,"pivot":{"x":-14.298442840576172,"y":4.436309814453125,"z":65.4644775390625},"rotation":{"x":0.07350339740514755,"y":-0.42409440875053408,"z":0.03455430269241333,"w":0.9019845724105835},"size":33.79780960083008,"orthographic":false}